LICENSE
README.md
setup.cfg
setup.py
timeloading/__init__.py
timeloading.egg-info/PKG-INFO
timeloading.egg-info/SOURCES.txt
timeloading.egg-info/dependency_links.txt
timeloading.egg-info/top_level.txt