Metadata-Version: 2.1
Name: timeloading
Version: 0.0.1
Summary: Animated loading bar. This package is a loading bar that appears when a specific function is run an animation and text. This bar is stoped to run after the function has finished working. You can control the shape and the waiting message, even the animation and its colors.
Home-page: https://yasserbdj96.github.io/
Author: YasserBDJ96
Author-email: yasser.bdj96@gmail.com
License: MIT License
Project-URL: Source Code, https://github.com/yasserbdj96/timeloading
Project-URL: Instagram, https://www.instagram.com/yasserbdj96/
Keywords: yasserbdj96,python,loading,bar
Platform: UNKNOWN
Classifier: Development Status :: 5 - Production/Stable
Classifier: Intended Audience :: Developers
Classifier: License :: OSI Approved :: MIT License
Classifier: Programming Language :: Python :: 3
Classifier: Operating System :: Unix
Classifier: Operating System :: MacOS :: MacOS X
Classifier: Operating System :: Microsoft :: Windows
Classifier: Topic :: Software Development :: Build Tools
Classifier: Topic :: Software Development :: Libraries :: Python Modules
Classifier: Topic :: Communications :: Email
Requires-Python: >=3.x.x
License-File: LICENSE
